datefinder.py
datefinder_lexpredict-0.6.2.1.dist-info/LICENSE
datefinder_lexpredict-0.6.2.1.dist-info/METADATA
datefinder_lexpredict-0.6.2.1.dist-info/WHEEL
datefinder_lexpredict-0.6.2.1.dist-info/top_level.txt
datefinder_lexpredict-0.6.2.1.dist-info/RECORD
