Metadata-Version: 2.1
Name: datefinder-lexpredict
Version: 0.6.2.1
Summary: Extract datetime objects from strings (LexPredict fork)
Home-page: https://github.com/LexPredict/datefinder
Author: ContraxSuite, LLC
Author-email: support@contraxsuite.com
License: MIT
Keywords: datetime parser nlp
Platform: UNKNOWN
Classifier: Development Status :: 4 - Beta
Classifier: Intended Audience :: Developers
Classifier: License :: OSI Approved :: MIT License
Classifier: Programming Language :: Python :: 2
Classifier: Programming Language :: Python :: 2.7
Classifier: Programming Language :: Python :: 3
Classifier: Programming Language :: Python :: 3.3
Classifier: Programming Language :: Python :: 3.4
Classifier: Programming Language :: Python :: 3.5
Classifier: Natural Language :: English
Requires-Dist: regex (==2020.7.14)
Requires-Dist: python-dateutil (>=2.4.2)
Requires-Dist: pytz
Provides-Extra: dev
Requires-Dist: pytest (>=2.8.5) ; extra == 'dev'
Requires-Dist: mock ; extra == 'dev'
Requires-Dist: pytz (>=2015.7) ; extra == 'dev'
Provides-Extra: test
Requires-Dist: pytest (>=2.8.5) ; extra == 'test'
Requires-Dist: mock ; extra == 'test'
Requires-Dist: pytz (>=2015.7) ; extra == 'test'
